[
  {
    "id": 19391884,
    "date": "2023-11-30",
    "report_name": "os",
    "report_agency": null,
    "os": "iOS",
    "visits": 18809314
  },
  {
    "id": 19391885,
    "date": "2023-11-30",
    "report_name": "os",
    "report_agency": null,
    "os": "Windows",
    "visits": 16283033
  },
  {
    "id": 19391886,
    "date": "2023-11-30",
    "report_name": "os",
    "report_agency": null,
    "os": "Android",
    "visits": 9209023
  },
  {
    "id": 19391887,
    "date": "2023-11-30",
    "report_name": "os",
    "report_agency": null,
    "os": "Macintosh",
    "visits": 4922692
  },
  {
    "id": 19391888,
    "date": "2023-11-30",
    "report_name": "os",
    "report_agency": null,
    "os": "Chrome OS",
    "visits": 1298595
  },
  {
    "id": 19391889,
    "date": "2023-11-30",
    "report_name": "os",
    "report_agency": null,
    "os": "Linux",
    "visits": 1061376
  },
  {
    "id": 19391890,
    "date": "2023-11-30",
    "report_name": "os",
    "report_agency": null,
    "os": "(not set)",
    "visits": 34858
  },
  {
    "id": 19391891,
    "date": "2023-11-30",
    "report_name": "os",
    "report_agency": null,
    "os": "Tizen",
    "visits": 1330
  },
  {
    "id": 19391892,
    "date": "2023-11-30",
    "report_name": "os",
    "report_agency": null,
    "os": "OS/2",
    "visits": 698
  },
  {
    "id": 19391893,
    "date": "2023-11-30",
    "report_name": "os",
    "report_agency": null,
    "os": "Fuchsia",
    "visits": 558
  },
  {
    "id": 19391894,
    "date": "2023-11-30",
    "report_name": "os",
    "report_agency": null,
    "os": "Firefox OS",
    "visits": 500
  },
  {
    "id": 19391895,
    "date": "2023-11-30",
    "report_name": "os",
    "report_agency": null,
    "os": "Playstation 4",
    "visits": 361
  },
  {
    "id": 19391896,
    "date": "2023-11-30",
    "report_name": "os",
    "report_agency": null,
    "os": "BlackBerry",
    "visits": 119
  },
  {
    "id": 19391897,
    "date": "2023-11-30",
    "report_name": "os",
    "report_agency": null,
    "os": "FreeBSD",
    "visits": 77
  },
  {
    "id": 19346272,
    "date": "2023-11-29",
    "report_name": "os",
    "report_agency": null,
    "os": "iOS",
    "visits": 18920876
  },
  {
    "id": 19346273,
    "date": "2023-11-29",
    "report_name": "os",
    "report_agency": null,
    "os": "Windows",
    "visits": 15743124
  },
  {
    "id": 19346274,
    "date": "2023-11-29",
    "report_name": "os",
    "report_agency": null,
    "os": "Android",
    "visits": 8908012
  },
  {
    "id": 19346275,
    "date": "2023-11-29",
    "report_name": "os",
    "report_agency": null,
    "os": "Macintosh",
    "visits": 4956169
  },
  {
    "id": 19346276,
    "date": "2023-11-29",
    "report_name": "os",
    "report_agency": null,
    "os": "Chrome OS",
    "visits": 1240160
  },
  {
    "id": 19346277,
    "date": "2023-11-29",
    "report_name": "os",
    "report_agency": null,
    "os": "Linux",
    "visits": 1035103
  },
  {
    "id": 19346278,
    "date": "2023-11-29",
    "report_name": "os",
    "report_agency": null,
    "os": "(not set)",
    "visits": 31599
  },
  {
    "id": 19346279,
    "date": "2023-11-29",
    "report_name": "os",
    "report_agency": null,
    "os": "Tizen",
    "visits": 899
  },
  {
    "id": 19346280,
    "date": "2023-11-29",
    "report_name": "os",
    "report_agency": null,
    "os": "OS/2",
    "visits": 593
  },
  {
    "id": 19346281,
    "date": "2023-11-29",
    "report_name": "os",
    "report_agency": null,
    "os": "Fuchsia",
    "visits": 580
  },
  {
    "id": 19346282,
    "date": "2023-11-29",
    "report_name": "os",
    "report_agency": null,
    "os": "Firefox OS",
    "visits": 466
  },
  {
    "id": 19346283,
    "date": "2023-11-29",
    "report_name": "os",
    "report_agency": null,
    "os": "Playstation 4",
    "visits": 335
  },
  {
    "id": 19346284,
    "date": "2023-11-29",
    "report_name": "os",
    "report_agency": null,
    "os": "BlackBerry",
    "visits": 109
  },
  {
    "id": 19346285,
    "date": "2023-11-29",
    "report_name": "os",
    "report_agency": null,
    "os": "FreeBSD",
    "visits": 91
  },
  {
    "id": 19346286,
    "date": "2023-11-29",
    "report_name": "os",
    "report_agency": null,
    "os": "UNIX",
    "visits": 72
  },
  {
    "id": 19300487,
    "date": "2023-11-28",
    "report_name": "os",
    "report_agency": null,
    "os": "iOS",
    "visits": 17826241
  },
  {
    "id": 19300488,
    "date": "2023-11-28",
    "report_name": "os",
    "report_agency": null,
    "os": "Windows",
    "visits": 15508269
  },
  {
    "id": 19300489,
    "date": "2023-11-28",
    "report_name": "os",
    "report_agency": null,
    "os": "Android",
    "visits": 8512451
  },
  {
    "id": 19300490,
    "date": "2023-11-28",
    "report_name": "os",
    "report_agency": null,
    "os": "Macintosh",
    "visits": 5129837
  },
  {
    "id": 19300491,
    "date": "2023-11-28",
    "report_name": "os",
    "report_agency": null,
    "os": "Chrome OS",
    "visits": 1243361
  },
  {
    "id": 19300492,
    "date": "2023-11-28",
    "report_name": "os",
    "report_agency": null,
    "os": "Linux",
    "visits": 1081728
  },
  {
    "id": 19300493,
    "date": "2023-11-28",
    "report_name": "os",
    "report_agency": null,
    "os": "(not set)",
    "visits": 37324
  },
  {
    "id": 19300494,
    "date": "2023-11-28",
    "report_name": "os",
    "report_agency": null,
    "os": "Tizen",
    "visits": 892
  },
  {
    "id": 19300495,
    "date": "2023-11-28",
    "report_name": "os",
    "report_agency": null,
    "os": "OS/2",
    "visits": 633
  },
  {
    "id": 19300496,
    "date": "2023-11-28",
    "report_name": "os",
    "report_agency": null,
    "os": "Fuchsia",
    "visits": 601
  },
  {
    "id": 19300497,
    "date": "2023-11-28",
    "report_name": "os",
    "report_agency": null,
    "os": "Firefox OS",
    "visits": 440
  },
  {
    "id": 19300498,
    "date": "2023-11-28",
    "report_name": "os",
    "report_agency": null,
    "os": "Playstation 4",
    "visits": 333
  },
  {
    "id": 19300499,
    "date": "2023-11-28",
    "report_name": "os",
    "report_agency": null,
    "os": "BlackBerry",
    "visits": 128
  },
  {
    "id": 19300500,
    "date": "2023-11-28",
    "report_name": "os",
    "report_agency": null,
    "os": "FreeBSD",
    "visits": 95
  },
  {
    "id": 19255538,
    "date": "2023-11-27",
    "report_name": "os",
    "report_agency": null,
    "os": "iOS",
    "visits": 17441512
  },
  {
    "id": 19255539,
    "date": "2023-11-27",
    "report_name": "os",
    "report_agency": null,
    "os": "Windows",
    "visits": 16362945
  },
  {
    "id": 19255540,
    "date": "2023-11-27",
    "report_name": "os",
    "report_agency": null,
    "os": "Android",
    "visits": 8519500
  },
  {
    "id": 19255541,
    "date": "2023-11-27",
    "report_name": "os",
    "report_agency": null,
    "os": "Macintosh",
    "visits": 5019810
  },
  {
    "id": 19255542,
    "date": "2023-11-27",
    "report_name": "os",
    "report_agency": null,
    "os": "Chrome OS",
    "visits": 1119338
  },
  {
    "id": 19255543,
    "date": "2023-11-27",
    "report_name": "os",
    "report_agency": null,
    "os": "Linux",
    "visits": 1011158
  },
  {
    "id": 19255544,
    "date": "2023-11-27",
    "report_name": "os",
    "report_agency": null,
    "os": "(not set)",
    "visits": 33542
  },
  {
    "id": 19255545,
    "date": "2023-11-27",
    "report_name": "os",
    "report_agency": null,
    "os": "Tizen",
    "visits": 910
  },
  {
    "id": 19255546,
    "date": "2023-11-27",
    "report_name": "os",
    "report_agency": null,
    "os": "OS/2",
    "visits": 609
  },
  {
    "id": 19255547,
    "date": "2023-11-27",
    "report_name": "os",
    "report_agency": null,
    "os": "Fuchsia",
    "visits": 566
  },
  {
    "id": 19255548,
    "date": "2023-11-27",
    "report_name": "os",
    "report_agency": null,
    "os": "Firefox OS",
    "visits": 462
  },
  {
    "id": 19255549,
    "date": "2023-11-27",
    "report_name": "os",
    "report_agency": null,
    "os": "Playstation 4",
    "visits": 304
  },
  {
    "id": 19255550,
    "date": "2023-11-27",
    "report_name": "os",
    "report_agency": null,
    "os": "BlackBerry",
    "visits": 114
  },
  {
    "id": 19255551,
    "date": "2023-11-27",
    "report_name": "os",
    "report_agency": null,
    "os": "FreeBSD",
    "visits": 106
  },
  {
    "id": 19255552,
    "date": "2023-11-27",
    "report_name": "os",
    "report_agency": null,
    "os": "OpenBSD",
    "visits": 53
  },
  {
    "id": 19220419,
    "date": "2023-11-26",
    "report_name": "os",
    "report_agency": null,
    "os": "iOS",
    "visits": 11883302
  },
  {
    "id": 19220420,
    "date": "2023-11-26",
    "report_name": "os",
    "report_agency": null,
    "os": "Android",
    "visits": 6338163
  },
  {
    "id": 19220421,
    "date": "2023-11-26",
    "report_name": "os",
    "report_agency": null,
    "os": "Windows",
    "visits": 5714550
  },
  {
    "id": 19220422,
    "date": "2023-11-26",
    "report_name": "os",
    "report_agency": null,
    "os": "Macintosh",
    "visits": 2978576
  },
  {
    "id": 19220423,
    "date": "2023-11-26",
    "report_name": "os",
    "report_agency": null,
    "os": "Linux",
    "visits": 816608
  },
  {
    "id": 19220424,
    "date": "2023-11-26",
    "report_name": "os",
    "report_agency": null,
    "os": "Chrome OS",
    "visits": 347851
  },
  {
    "id": 19220425,
    "date": "2023-11-26",
    "report_name": "os",
    "report_agency": null,
    "os": "(not set)",
    "visits": 25769
  },
  {
    "id": 19220426,
    "date": "2023-11-26",
    "report_name": "os",
    "report_agency": null,
    "os": "Tizen",
    "visits": 955
  },
  {
    "id": 19220427,
    "date": "2023-11-26",
    "report_name": "os",
    "report_agency": null,
    "os": "Fuchsia",
    "visits": 656
  },
  {
    "id": 19220428,
    "date": "2023-11-26",
    "report_name": "os",
    "report_agency": null,
    "os": "OS/2",
    "visits": 643
  },
  {
    "id": 19220429,
    "date": "2023-11-26",
    "report_name": "os",
    "report_agency": null,
    "os": "Firefox OS",
    "visits": 472
  },
  {
    "id": 19220430,
    "date": "2023-11-26",
    "report_name": "os",
    "report_agency": null,
    "os": "Playstation 4",
    "visits": 296
  },
  {
    "id": 19220431,
    "date": "2023-11-26",
    "report_name": "os",
    "report_agency": null,
    "os": "BlackBerry",
    "visits": 85
  },
  {
    "id": 19220432,
    "date": "2023-11-26",
    "report_name": "os",
    "report_agency": null,
    "os": "FreeBSD",
    "visits": 68
  },
  {
    "id": 19187066,
    "date": "2023-11-25",
    "report_name": "os",
    "report_agency": null,
    "os": "iOS",
    "visits": 13040965
  },
  {
    "id": 19187067,
    "date": "2023-11-25",
    "report_name": "os",
    "report_agency": null,
    "os": "Android",
    "visits": 6818507
  },
  {
    "id": 19187068,
    "date": "2023-11-25",
    "report_name": "os",
    "report_agency": null,
    "os": "Windows",
    "visits": 4968173
  },
  {
    "id": 19187069,
    "date": "2023-11-25",
    "report_name": "os",
    "report_agency": null,
    "os": "Macintosh",
    "visits": 2539208
  },
  {
    "id": 19187070,
    "date": "2023-11-25",
    "report_name": "os",
    "report_agency": null,
    "os": "Linux",
    "visits": 851601
  },
  {
    "id": 19187071,
    "date": "2023-11-25",
    "report_name": "os",
    "report_agency": null,
    "os": "Chrome OS",
    "visits": 271050
  },
  {
    "id": 19187072,
    "date": "2023-11-25",
    "report_name": "os",
    "report_agency": null,
    "os": "(not set)",
    "visits": 22595
  },
  {
    "id": 19187073,
    "date": "2023-11-25",
    "report_name": "os",
    "report_agency": null,
    "os": "Tizen",
    "visits": 823
  },
  {
    "id": 19187074,
    "date": "2023-11-25",
    "report_name": "os",
    "report_agency": null,
    "os": "OS/2",
    "visits": 587
  },
  {
    "id": 19187075,
    "date": "2023-11-25",
    "report_name": "os",
    "report_agency": null,
    "os": "Fuchsia",
    "visits": 504
  },
  {
    "id": 19187076,
    "date": "2023-11-25",
    "report_name": "os",
    "report_agency": null,
    "os": "Firefox OS",
    "visits": 414
  },
  {
    "id": 19187077,
    "date": "2023-11-25",
    "report_name": "os",
    "report_agency": null,
    "os": "Playstation 4",
    "visits": 332
  },
  {
    "id": 19187078,
    "date": "2023-11-25",
    "report_name": "os",
    "report_agency": null,
    "os": "BlackBerry",
    "visits": 121
  },
  {
    "id": 19187079,
    "date": "2023-11-25",
    "report_name": "os",
    "report_agency": null,
    "os": "FreeBSD",
    "visits": 62
  },
  {
    "id": 19151582,
    "date": "2023-11-24",
    "report_name": "os",
    "report_agency": null,
    "os": "iOS",
    "visits": 13953271
  },
  {
    "id": 19151583,
    "date": "2023-11-24",
    "report_name": "os",
    "report_agency": null,
    "os": "Android",
    "visits": 7273453
  },
  {
    "id": 19151584,
    "date": "2023-11-24",
    "report_name": "os",
    "report_agency": null,
    "os": "Windows",
    "visits": 6856532
  },
  {
    "id": 19151585,
    "date": "2023-11-24",
    "report_name": "os",
    "report_agency": null,
    "os": "Macintosh",
    "visits": 2723137
  },
  {
    "id": 19151586,
    "date": "2023-11-24",
    "report_name": "os",
    "report_agency": null,
    "os": "Linux",
    "visits": 891993
  },
  {
    "id": 19151587,
    "date": "2023-11-24",
    "report_name": "os",
    "report_agency": null,
    "os": "Chrome OS",
    "visits": 298308
  },
  {
    "id": 19151588,
    "date": "2023-11-24",
    "report_name": "os",
    "report_agency": null,
    "os": "(not set)",
    "visits": 26405
  },
  {
    "id": 19151589,
    "date": "2023-11-24",
    "report_name": "os",
    "report_agency": null,
    "os": "Tizen",
    "visits": 924
  },
  {
    "id": 19151590,
    "date": "2023-11-24",
    "report_name": "os",
    "report_agency": null,
    "os": "OS/2",
    "visits": 590
  },
  {
    "id": 19151591,
    "date": "2023-11-24",
    "report_name": "os",
    "report_agency": null,
    "os": "Fuchsia",
    "visits": 497
  },
  {
    "id": 19151592,
    "date": "2023-11-24",
    "report_name": "os",
    "report_agency": null,
    "os": "Firefox OS",
    "visits": 448
  },
  {
    "id": 19151593,
    "date": "2023-11-24",
    "report_name": "os",
    "report_agency": null,
    "os": "Playstation 4",
    "visits": 369
  },
  {
    "id": 19151594,
    "date": "2023-11-24",
    "report_name": "os",
    "report_agency": null,
    "os": "BlackBerry",
    "visits": 111
  },
  {
    "id": 19151595,
    "date": "2023-11-24",
    "report_name": "os",
    "report_agency": null,
    "os": "FreeBSD",
    "visits": 83
  },
  {
    "id": 19117473,
    "date": "2023-11-23",
    "report_name": "os",
    "report_agency": null,
    "os": "iOS",
    "visits": 10261966
  },
  {
    "id": 19117474,
    "date": "2023-11-23",
    "report_name": "os",
    "report_agency": null,
    "os": "Android",
    "visits": 5903893
  },
  {
    "id": 19117475,
    "date": "2023-11-23",
    "report_name": "os",
    "report_agency": null,
    "os": "Windows",
    "visits": 4979504
  },
  {
    "id": 19117476,
    "date": "2023-11-23",
    "report_name": "os",
    "report_agency": null,
    "os": "Macintosh",
    "visits": 2073245
  },
  {
    "id": 19117477,
    "date": "2023-11-23",
    "report_name": "os",
    "report_agency": null,
    "os": "Linux",
    "visits": 954345
  },
  {
    "id": 19117478,
    "date": "2023-11-23",
    "report_name": "os",
    "report_agency": null,
    "os": "Chrome OS",
    "visits": 260846
  },
  {
    "id": 19117479,
    "date": "2023-11-23",
    "report_name": "os",
    "report_agency": null,
    "os": "(not set)",
    "visits": 30774
  },
  {
    "id": 19117480,
    "date": "2023-11-23",
    "report_name": "os",
    "report_agency": null,
    "os": "Tizen",
    "visits": 858
  },
  {
    "id": 19117481,
    "date": "2023-11-23",
    "report_name": "os",
    "report_agency": null,
    "os": "OS/2",
    "visits": 492
  },
  {
    "id": 19117482,
    "date": "2023-11-23",
    "report_name": "os",
    "report_agency": null,
    "os": "Fuchsia",
    "visits": 454
  },
  {
    "id": 19117483,
    "date": "2023-11-23",
    "report_name": "os",
    "report_agency": null,
    "os": "Firefox OS",
    "visits": 361
  },
  {
    "id": 19117484,
    "date": "2023-11-23",
    "report_name": "os",
    "report_agency": null,
    "os": "Playstation 4",
    "visits": 354
  },
  {
    "id": 19117485,
    "date": "2023-11-23",
    "report_name": "os",
    "report_agency": null,
    "os": "BlackBerry",
    "visits": 106
  },
  {
    "id": 19117486,
    "date": "2023-11-23",
    "report_name": "os",
    "report_agency": null,
    "os": "FreeBSD",
    "visits": 97
  },
  {
    "id": 19076399,
    "date": "2023-11-22",
    "report_name": "os",
    "report_agency": null,
    "os": "iOS",
    "visits": 14779729
  },
  {
    "id": 19076400,
    "date": "2023-11-22",
    "report_name": "os",
    "report_agency": null,
    "os": "Windows",
    "visits": 10996569
  },
  {
    "id": 19076401,
    "date": "2023-11-22",
    "report_name": "os",
    "report_agency": null,
    "os": "Android",
    "visits": 7966179
  },
  {
    "id": 19076402,
    "date": "2023-11-22",
    "report_name": "os",
    "report_agency": null,
    "os": "Macintosh",
    "visits": 3415038
  },
  {
    "id": 19076403,
    "date": "2023-11-22",
    "report_name": "os",
    "report_agency": null,
    "os": "Linux",
    "visits": 1065668
  },
  {
    "id": 19076404,
    "date": "2023-11-22",
    "report_name": "os",
    "report_agency": null,
    "os": "Chrome OS",
    "visits": 398363
  },
  {
    "id": 19076405,
    "date": "2023-11-22",
    "report_name": "os",
    "report_agency": null,
    "os": "(not set)",
    "visits": 26644
  },
  {
    "id": 19076406,
    "date": "2023-11-22",
    "report_name": "os",
    "report_agency": null,
    "os": "Tizen",
    "visits": 962
  },
  {
    "id": 19076407,
    "date": "2023-11-22",
    "report_name": "os",
    "report_agency": null,
    "os": "OS/2",
    "visits": 566
  },
  {
    "id": 19076408,
    "date": "2023-11-22",
    "report_name": "os",
    "report_agency": null,
    "os": "Fuchsia",
    "visits": 538
  },
  {
    "id": 19076409,
    "date": "2023-11-22",
    "report_name": "os",
    "report_agency": null,
    "os": "Firefox OS",
    "visits": 377
  },
  {
    "id": 19076410,
    "date": "2023-11-22",
    "report_name": "os",
    "report_agency": null,
    "os": "Playstation 4",
    "visits": 352
  },
  {
    "id": 19076411,
    "date": "2023-11-22",
    "report_name": "os",
    "report_agency": null,
    "os": "FreeBSD",
    "visits": 112
  },
  {
    "id": 19076412,
    "date": "2023-11-22",
    "report_name": "os",
    "report_agency": null,
    "os": "BlackBerry",
    "visits": 110
  },
  {
    "id": 19076413,
    "date": "2023-11-22",
    "report_name": "os",
    "report_agency": null,
    "os": "UNIX",
    "visits": 59
  },
  {
    "id": 19076414,
    "date": "2023-11-22",
    "report_name": "os",
    "report_agency": null,
    "os": "Samsung",
    "visits": 55
  },
  {
    "id": 19032160,
    "date": "2023-11-21",
    "report_name": "os",
    "report_agency": null,
    "os": "iOS",
    "visits": 16044465
  },
  {
    "id": 19032161,
    "date": "2023-11-21",
    "report_name": "os",
    "report_agency": null,
    "os": "Windows",
    "visits": 14162144
  },
  {
    "id": 19032162,
    "date": "2023-11-21",
    "report_name": "os",
    "report_agency": null,
    "os": "Android",
    "visits": 8379026
  },
  {
    "id": 19032163,
    "date": "2023-11-21",
    "report_name": "os",
    "report_agency": null,
    "os": "Macintosh",
    "visits": 4145913
  },
  {
    "id": 19032164,
    "date": "2023-11-21",
    "report_name": "os",
    "report_agency": null,
    "os": "Linux",
    "visits": 1188196
  },
  {
    "id": 19032165,
    "date": "2023-11-21",
    "report_name": "os",
    "report_agency": null,
    "os": "Chrome OS",
    "visits": 707210
  },
  {
    "id": 19032166,
    "date": "2023-11-21",
    "report_name": "os",
    "report_agency": null,
    "os": "(not set)",
    "visits": 28250
  },
  {
    "id": 19032167,
    "date": "2023-11-21",
    "report_name": "os",
    "report_agency": null,
    "os": "Tizen",
    "visits": 986
  },
  {
    "id": 19032168,
    "date": "2023-11-21",
    "report_name": "os",
    "report_agency": null,
    "os": "OS/2",
    "visits": 719
  },
  {
    "id": 19032169,
    "date": "2023-11-21",
    "report_name": "os",
    "report_agency": null,
    "os": "Fuchsia",
    "visits": 592
  },
  {
    "id": 19032170,
    "date": "2023-11-21",
    "report_name": "os",
    "report_agency": null,
    "os": "Firefox OS",
    "visits": 494
  },
  {
    "id": 19032171,
    "date": "2023-11-21",
    "report_name": "os",
    "report_agency": null,
    "os": "Playstation 4",
    "visits": 406
  },
  {
    "id": 19032172,
    "date": "2023-11-21",
    "report_name": "os",
    "report_agency": null,
    "os": "BlackBerry",
    "visits": 124
  },
  {
    "id": 19032173,
    "date": "2023-11-21",
    "report_name": "os",
    "report_agency": null,
    "os": "FreeBSD",
    "visits": 113
  },
  {
    "id": 18987844,
    "date": "2023-11-20",
    "report_name": "os",
    "report_agency": null,
    "os": "iOS",
    "visits": 17554026
  },
  {
    "id": 18987845,
    "date": "2023-11-20",
    "report_name": "os",
    "report_agency": null,
    "os": "Windows",
    "visits": 14410747
  },
  {
    "id": 18987846,
    "date": "2023-11-20",
    "report_name": "os",
    "report_agency": null,
    "os": "Android",
    "visits": 8654557
  },
  {
    "id": 18987847,
    "date": "2023-11-20",
    "report_name": "os",
    "report_agency": null,
    "os": "Macintosh",
    "visits": 4529114
  },
  {
    "id": 18987848,
    "date": "2023-11-20",
    "report_name": "os",
    "report_agency": null,
    "os": "Linux",
    "visits": 1061196
  },
  {
    "id": 18987849,
    "date": "2023-11-20",
    "report_name": "os",
    "report_agency": null,
    "os": "Chrome OS",
    "visits": 846923
  },
  {
    "id": 18987850,
    "date": "2023-11-20",
    "report_name": "os",
    "report_agency": null,
    "os": "(not set)",
    "visits": 30186
  },
  {
    "id": 18987851,
    "date": "2023-11-20",
    "report_name": "os",
    "report_agency": null,
    "os": "Tizen",
    "visits": 976
  },
  {
    "id": 18987852,
    "date": "2023-11-20",
    "report_name": "os",
    "report_agency": null,
    "os": "OS/2",
    "visits": 717
  },
  {
    "id": 18987853,
    "date": "2023-11-20",
    "report_name": "os",
    "report_agency": null,
    "os": "Fuchsia",
    "visits": 603
  },
  {
    "id": 18987854,
    "date": "2023-11-20",
    "report_name": "os",
    "report_agency": null,
    "os": "Firefox OS",
    "visits": 494
  },
  {
    "id": 18987855,
    "date": "2023-11-20",
    "report_name": "os",
    "report_agency": null,
    "os": "Playstation 4",
    "visits": 404
  },
  {
    "id": 18987856,
    "date": "2023-11-20",
    "report_name": "os",
    "report_agency": null,
    "os": "FreeBSD",
    "visits": 136
  },
  {
    "id": 18987857,
    "date": "2023-11-20",
    "report_name": "os",
    "report_agency": null,
    "os": "BlackBerry",
    "visits": 129
  },
  {
    "id": 18952968,
    "date": "2023-11-19",
    "report_name": "os",
    "report_agency": null,
    "os": "iOS",
    "visits": 11137694
  },
  {
    "id": 18952969,
    "date": "2023-11-19",
    "report_name": "os",
    "report_agency": null,
    "os": "Android",
    "visits": 6218273
  },
  {
    "id": 18952970,
    "date": "2023-11-19",
    "report_name": "os",
    "report_agency": null,
    "os": "Windows",
    "visits": 5320607
  },
  {
    "id": 18952971,
    "date": "2023-11-19",
    "report_name": "os",
    "report_agency": null,
    "os": "Macintosh",
    "visits": 2885468
  },
  {
    "id": 18952972,
    "date": "2023-11-19",
    "report_name": "os",
    "report_agency": null,
    "os": "Linux",
    "visits": 800164
  },
  {
    "id": 18952973,
    "date": "2023-11-19",
    "report_name": "os",
    "report_agency": null,
    "os": "Chrome OS",
    "visits": 336349
  },
  {
    "id": 18952974,
    "date": "2023-11-19",
    "report_name": "os",
    "report_agency": null,
    "os": "(not set)",
    "visits": 20700
  },
  {
    "id": 18952975,
    "date": "2023-11-19",
    "report_name": "os",
    "report_agency": null,
    "os": "Tizen",
    "visits": 914
  },
  {
    "id": 18952976,
    "date": "2023-11-19",
    "report_name": "os",
    "report_agency": null,
    "os": "Fuchsia",
    "visits": 575
  },
  {
    "id": 18952977,
    "date": "2023-11-19",
    "report_name": "os",
    "report_agency": null,
    "os": "OS/2",
    "visits": 546
  },
  {
    "id": 18952978,
    "date": "2023-11-19",
    "report_name": "os",
    "report_agency": null,
    "os": "Firefox OS",
    "visits": 378
  },
  {
    "id": 18952979,
    "date": "2023-11-19",
    "report_name": "os",
    "report_agency": null,
    "os": "Playstation 4",
    "visits": 360
  },
  {
    "id": 18952980,
    "date": "2023-11-19",
    "report_name": "os",
    "report_agency": null,
    "os": "FreeBSD",
    "visits": 105
  },
  {
    "id": 18952981,
    "date": "2023-11-19",
    "report_name": "os",
    "report_agency": null,
    "os": "BlackBerry",
    "visits": 93
  },
  {
    "id": 18918653,
    "date": "2023-11-18",
    "report_name": "os",
    "report_agency": null,
    "os": "iOS",
    "visits": 12769326
  },
  {
    "id": 18918654,
    "date": "2023-11-18",
    "report_name": "os",
    "report_agency": null,
    "os": "Android",
    "visits": 6740314
  },
  {
    "id": 18918655,
    "date": "2023-11-18",
    "report_name": "os",
    "report_agency": null,
    "os": "Windows",
    "visits": 5301597
  },
  {
    "id": 18918656,
    "date": "2023-11-18",
    "report_name": "os",
    "report_agency": null,
    "os": "Macintosh",
    "visits": 2672125
  },
  {
    "id": 18918657,
    "date": "2023-11-18",
    "report_name": "os",
    "report_agency": null,
    "os": "Linux",
    "visits": 855287
  },
  {
    "id": 18918658,
    "date": "2023-11-18",
    "report_name": "os",
    "report_agency": null,
    "os": "Chrome OS",
    "visits": 301300
  },
  {
    "id": 18918659,
    "date": "2023-11-18",
    "report_name": "os",
    "report_agency": null,
    "os": "(not set)",
    "visits": 20891
  },
  {
    "id": 18918660,
    "date": "2023-11-18",
    "report_name": "os",
    "report_agency": null,
    "os": "Tizen",
    "visits": 1107
  },
  {
    "id": 18918661,
    "date": "2023-11-18",
    "report_name": "os",
    "report_agency": null,
    "os": "OS/2",
    "visits": 527
  },
  {
    "id": 18918662,
    "date": "2023-11-18",
    "report_name": "os",
    "report_agency": null,
    "os": "Fuchsia",
    "visits": 483
  },
  {
    "id": 18918663,
    "date": "2023-11-18",
    "report_name": "os",
    "report_agency": null,
    "os": "Playstation 4",
    "visits": 354
  },
  {
    "id": 18918664,
    "date": "2023-11-18",
    "report_name": "os",
    "report_agency": null,
    "os": "Firefox OS",
    "visits": 353
  },
  {
    "id": 18918665,
    "date": "2023-11-18",
    "report_name": "os",
    "report_agency": null,
    "os": "FreeBSD",
    "visits": 102
  },
  {
    "id": 18918666,
    "date": "2023-11-18",
    "report_name": "os",
    "report_agency": null,
    "os": "BlackBerry",
    "visits": 78
  },
  {
    "id": 18876696,
    "date": "2023-11-17",
    "report_name": "os",
    "report_agency": null,
    "os": "iOS",
    "visits": 15438836
  },
  {
    "id": 18876697,
    "date": "2023-11-17",
    "report_name": "os",
    "report_agency": null,
    "os": "Windows",
    "visits": 12252823
  },
  {
    "id": 18876698,
    "date": "2023-11-17",
    "report_name": "os",
    "report_agency": null,
    "os": "Android",
    "visits": 7815337
  },
  {
    "id": 18876699,
    "date": "2023-11-17",
    "report_name": "os",
    "report_agency": null,
    "os": "Macintosh",
    "visits": 4018188
  },
  {
    "id": 18876700,
    "date": "2023-11-17",
    "report_name": "os",
    "report_agency": null,
    "os": "Linux",
    "visits": 1005977
  },
  {
    "id": 18876701,
    "date": "2023-11-17",
    "report_name": "os",
    "report_agency": null,
    "os": "Chrome OS",
    "visits": 938605
  },
  {
    "id": 18876702,
    "date": "2023-11-17",
    "report_name": "os",
    "report_agency": null,
    "os": "(not set)",
    "visits": 28050
  },
  {
    "id": 18876703,
    "date": "2023-11-17",
    "report_name": "os",
    "report_agency": null,
    "os": "Tizen",
    "visits": 1036
  },
  {
    "id": 18876704,
    "date": "2023-11-17",
    "report_name": "os",
    "report_agency": null,
    "os": "OS/2",
    "visits": 587
  },
  {
    "id": 18876705,
    "date": "2023-11-17",
    "report_name": "os",
    "report_agency": null,
    "os": "Fuchsia",
    "visits": 516
  },
  {
    "id": 18876706,
    "date": "2023-11-17",
    "report_name": "os",
    "report_agency": null,
    "os": "Firefox OS",
    "visits": 436
  },
  {
    "id": 18876707,
    "date": "2023-11-17",
    "report_name": "os",
    "report_agency": null,
    "os": "Playstation 4",
    "visits": 396
  },
  {
    "id": 18876708,
    "date": "2023-11-17",
    "report_name": "os",
    "report_agency": null,
    "os": "FreeBSD",
    "visits": 118
  },
  {
    "id": 18876709,
    "date": "2023-11-17",
    "report_name": "os",
    "report_agency": null,
    "os": "BlackBerry",
    "visits": 115
  },
  {
    "id": 18831812,
    "date": "2023-11-16",
    "report_name": "os",
    "report_agency": null,
    "os": "iOS",
    "visits": 16619714
  },
  {
    "id": 18831813,
    "date": "2023-11-16",
    "report_name": "os",
    "report_agency": null,
    "os": "Windows",
    "visits": 14793508
  },
  {
    "id": 18831814,
    "date": "2023-11-16",
    "report_name": "os",
    "report_agency": null,
    "os": "Android",
    "visits": 8336425
  },
  {
    "id": 18831815,
    "date": "2023-11-16",
    "report_name": "os",
    "report_agency": null,
    "os": "Macintosh",
    "visits": 4470814
  },
  {
    "id": 18831816,
    "date": "2023-11-16",
    "report_name": "os",
    "report_agency": null,
    "os": "Chrome OS",
    "visits": 1196845
  },
  {
    "id": 18831817,
    "date": "2023-11-16",
    "report_name": "os",
    "report_agency": null,
    "os": "Linux",
    "visits": 1064172
  },
  {
    "id": 18831818,
    "date": "2023-11-16",
    "report_name": "os",
    "report_agency": null,
    "os": "(not set)",
    "visits": 35648
  },
  {
    "id": 18831819,
    "date": "2023-11-16",
    "report_name": "os",
    "report_agency": null,
    "os": "Tizen",
    "visits": 1116
  },
  {
    "id": 18831820,
    "date": "2023-11-16",
    "report_name": "os",
    "report_agency": null,
    "os": "OS/2",
    "visits": 606
  },
  {
    "id": 18831821,
    "date": "2023-11-16",
    "report_name": "os",
    "report_agency": null,
    "os": "Fuchsia",
    "visits": 583
  },
  {
    "id": 18831822,
    "date": "2023-11-16",
    "report_name": "os",
    "report_agency": null,
    "os": "Firefox OS",
    "visits": 437
  },
  {
    "id": 18831823,
    "date": "2023-11-16",
    "report_name": "os",
    "report_agency": null,
    "os": "Playstation 4",
    "visits": 398
  },
  {
    "id": 18831824,
    "date": "2023-11-16",
    "report_name": "os",
    "report_agency": null,
    "os": "FreeBSD",
    "visits": 113
  },
  {
    "id": 18831825,
    "date": "2023-11-16",
    "report_name": "os",
    "report_agency": null,
    "os": "BlackBerry",
    "visits": 109
  },
  {
    "id": 18786467,
    "date": "2023-11-15",
    "report_name": "os",
    "report_agency": null,
    "os": "iOS",
    "visits": 16360090
  },
  {
    "id": 18786468,
    "date": "2023-11-15",
    "report_name": "os",
    "report_agency": null,
    "os": "Windows",
    "visits": 15133712
  },
  {
    "id": 18786469,
    "date": "2023-11-15",
    "report_name": "os",
    "report_agency": null,
    "os": "Android",
    "visits": 8261606
  },
  {
    "id": 18786470,
    "date": "2023-11-15",
    "report_name": "os",
    "report_agency": null,
    "os": "Macintosh",
    "visits": 4632424
  },
  {
    "id": 18786471,
    "date": "2023-11-15",
    "report_name": "os",
    "report_agency": null,
    "os": "Chrome OS",
    "visits": 1165505
  },
  {
    "id": 18786472,
    "date": "2023-11-15",
    "report_name": "os",
    "report_agency": null,
    "os": "Linux",
    "visits": 1044777
  },
  {
    "id": 18786473,
    "date": "2023-11-15",
    "report_name": "os",
    "report_agency": null,
    "os": "(not set)",
    "visits": 45577
  },
  {
    "id": 18786474,
    "date": "2023-11-15",
    "report_name": "os",
    "report_agency": null,
    "os": "Tizen",
    "visits": 1114
  },
  {
    "id": 18786475,
    "date": "2023-11-15",
    "report_name": "os",
    "report_agency": null,
    "os": "OS/2",
    "visits": 681
  },
  {
    "id": 18786476,
    "date": "2023-11-15",
    "report_name": "os",
    "report_agency": null,
    "os": "Fuchsia",
    "visits": 600
  },
  {
    "id": 18786477,
    "date": "2023-11-15",
    "report_name": "os",
    "report_agency": null,
    "os": "Firefox OS",
    "visits": 387
  },
  {
    "id": 18786478,
    "date": "2023-11-15",
    "report_name": "os",
    "report_agency": null,
    "os": "Playstation 4",
    "visits": 375
  },
  {
    "id": 18786479,
    "date": "2023-11-15",
    "report_name": "os",
    "report_agency": null,
    "os": "BlackBerry",
    "visits": 136
  },
  {
    "id": 18786480,
    "date": "2023-11-15",
    "report_name": "os",
    "report_agency": null,
    "os": "FreeBSD",
    "visits": 124
  },
  {
    "id": 18786481,
    "date": "2023-11-15",
    "report_name": "os",
    "report_agency": null,
    "os": "UNIX",
    "visits": 71
  },
  {
    "id": 18741114,
    "date": "2023-11-14",
    "report_name": "os",
    "report_agency": null,
    "os": "iOS",
    "visits": 15515933
  },
  {
    "id": 18741115,
    "date": "2023-11-14",
    "report_name": "os",
    "report_agency": null,
    "os": "Windows",
    "visits": 15129838
  },
  {
    "id": 18741116,
    "date": "2023-11-14",
    "report_name": "os",
    "report_agency": null,
    "os": "Android",
    "visits": 8060214
  },
  {
    "id": 18741117,
    "date": "2023-11-14",
    "report_name": "os",
    "report_agency": null,
    "os": "Macintosh",
    "visits": 4620894
  },
  {
    "id": 18741118,
    "date": "2023-11-14",
    "report_name": "os",
    "report_agency": null,
    "os": "Chrome OS",
    "visits": 1210479
  },
  {
    "id": 18741119,
    "date": "2023-11-14",
    "report_name": "os",
    "report_agency": null,
    "os": "Linux",
    "visits": 1095197
  },
  {
    "id": 18741120,
    "date": "2023-11-14",
    "report_name": "os",
    "report_agency": null,
    "os": "(not set)",
    "visits": 33461
  },
  {
    "id": 18741121,
    "date": "2023-11-14",
    "report_name": "os",
    "report_agency": null,
    "os": "Tizen",
    "visits": 1100
  },
  {
    "id": 18741122,
    "date": "2023-11-14",
    "report_name": "os",
    "report_agency": null,
    "os": "OS/2",
    "visits": 589
  },
  {
    "id": 18741123,
    "date": "2023-11-14",
    "report_name": "os",
    "report_agency": null,
    "os": "Fuchsia",
    "visits": 564
  },
  {
    "id": 18741124,
    "date": "2023-11-14",
    "report_name": "os",
    "report_agency": null,
    "os": "Firefox OS",
    "visits": 420
  },
  {
    "id": 18741125,
    "date": "2023-11-14",
    "report_name": "os",
    "report_agency": null,
    "os": "Playstation 4",
    "visits": 365
  },
  {
    "id": 18741126,
    "date": "2023-11-14",
    "report_name": "os",
    "report_agency": null,
    "os": "BlackBerry",
    "visits": 127
  },
  {
    "id": 18741127,
    "date": "2023-11-14",
    "report_name": "os",
    "report_agency": null,
    "os": "FreeBSD",
    "visits": 104
  },
  {
    "id": 18741128,
    "date": "2023-11-14",
    "report_name": "os",
    "report_agency": null,
    "os": "Samsung",
    "visits": 56
  },
  {
    "id": 18696024,
    "date": "2023-11-13",
    "report_name": "os",
    "report_agency": null,
    "os": "iOS",
    "visits": 17432474
  },
  {
    "id": 18696025,
    "date": "2023-11-13",
    "report_name": "os",
    "report_agency": null,
    "os": "Windows",
    "visits": 15071453
  },
  {
    "id": 18696026,
    "date": "2023-11-13",
    "report_name": "os",
    "report_agency": null,
    "os": "Android",
    "visits": 8767297
  },
  {
    "id": 18696027,
    "date": "2023-11-13",
    "report_name": "os",
    "report_agency": null,
    "os": "Macintosh",
    "visits": 4910302
  },
  {
    "id": 18696028,
    "date": "2023-11-13",
    "report_name": "os",
    "report_agency": null,
    "os": "Chrome OS",
    "visits": 1169353
  },
  {
    "id": 18696029,
    "date": "2023-11-13",
    "report_name": "os",
    "report_agency": null,
    "os": "Linux",
    "visits": 1058406
  },
  {
    "id": 18696030,
    "date": "2023-11-13",
    "report_name": "os",
    "report_agency": null,
    "os": "(not set)",
    "visits": 27395
  },
  {
    "id": 18696031,
    "date": "2023-11-13",
    "report_name": "os",
    "report_agency": null,
    "os": "Tizen",
    "visits": 1080
  },
  {
    "id": 18696032,
    "date": "2023-11-13",
    "report_name": "os",
    "report_agency": null,
    "os": "Fuchsia",
    "visits": 645
  },
  {
    "id": 18696033,
    "date": "2023-11-13",
    "report_name": "os",
    "report_agency": null,
    "os": "OS/2",
    "visits": 633
  },
  {
    "id": 18696034,
    "date": "2023-11-13",
    "report_name": "os",
    "report_agency": null,
    "os": "Firefox OS",
    "visits": 427
  },
  {
    "id": 18696035,
    "date": "2023-11-13",
    "report_name": "os",
    "report_agency": null,
    "os": "Playstation 4",
    "visits": 346
  },
  {
    "id": 18696036,
    "date": "2023-11-13",
    "report_name": "os",
    "report_agency": null,
    "os": "BlackBerry",
    "visits": 141
  },
  {
    "id": 18696037,
    "date": "2023-11-13",
    "report_name": "os",
    "report_agency": null,
    "os": "FreeBSD",
    "visits": 118
  },
  {
    "id": 18661045,
    "date": "2023-11-12",
    "report_name": "os",
    "report_agency": null,
    "os": "iOS",
    "visits": 11077100
  },
  {
    "id": 18661046,
    "date": "2023-11-12",
    "report_name": "os",
    "report_agency": null,
    "os": "Android",
    "visits": 5878486
  },
  {
    "id": 18661047,
    "date": "2023-11-12",
    "report_name": "os",
    "report_agency": null,
    "os": "Windows",
    "visits": 5312373
  },
  {
    "id": 18661048,
    "date": "2023-11-12",
    "report_name": "os",
    "report_agency": null,
    "os": "Macintosh",
    "visits": 2849761
  },
  {
    "id": 18661049,
    "date": "2023-11-12",
    "report_name": "os",
    "report_agency": null,
    "os": "Linux",
    "visits": 842746
  },
  {
    "id": 18661050,
    "date": "2023-11-12",
    "report_name": "os",
    "report_agency": null,
    "os": "Chrome OS",
    "visits": 360159
  },
  {
    "id": 18661051,
    "date": "2023-11-12",
    "report_name": "os",
    "report_agency": null,
    "os": "(not set)",
    "visits": 31278
  },
  {
    "id": 18661052,
    "date": "2023-11-12",
    "report_name": "os",
    "report_agency": null,
    "os": "Tizen",
    "visits": 1006
  },
  {
    "id": 18661053,
    "date": "2023-11-12",
    "report_name": "os",
    "report_agency": null,
    "os": "Fuchsia",
    "visits": 584
  },
  {
    "id": 18661054,
    "date": "2023-11-12",
    "report_name": "os",
    "report_agency": null,
    "os": "OS/2",
    "visits": 516
  },
  {
    "id": 18661055,
    "date": "2023-11-12",
    "report_name": "os",
    "report_agency": null,
    "os": "Firefox OS",
    "visits": 378
  },
  {
    "id": 18661056,
    "date": "2023-11-12",
    "report_name": "os",
    "report_agency": null,
    "os": "Playstation 4",
    "visits": 315
  },
  {
    "id": 18661057,
    "date": "2023-11-12",
    "report_name": "os",
    "report_agency": null,
    "os": "BlackBerry",
    "visits": 105
  },
  {
    "id": 18661058,
    "date": "2023-11-12",
    "report_name": "os",
    "report_agency": null,
    "os": "FreeBSD",
    "visits": 69
  },
  {
    "id": 18626770,
    "date": "2023-11-11",
    "report_name": "os",
    "report_agency": null,
    "os": "iOS",
    "visits": 11412539
  },
  {
    "id": 18626771,
    "date": "2023-11-11",
    "report_name": "os",
    "report_agency": null,
    "os": "Android",
    "visits": 6348723
  },
  {
    "id": 18626772,
    "date": "2023-11-11",
    "report_name": "os",
    "report_agency": null,
    "os": "Windows",
    "visits": 4979598
  },
  {
    "id": 18626773,
    "date": "2023-11-11",
    "report_name": "os",
    "report_agency": null,
    "os": "Macintosh",
    "visits": 2406758
  },
  {
    "id": 18626774,
    "date": "2023-11-11",
    "report_name": "os",
    "report_agency": null,
    "os": "Linux",
    "visits": 862256
  },
  {
    "id": 18626775,
    "date": "2023-11-11",
    "report_name": "os",
    "report_agency": null,
    "os": "Chrome OS",
    "visits": 294292
  },
  {
    "id": 18626776,
    "date": "2023-11-11",
    "report_name": "os",
    "report_agency": null,
    "os": "(not set)",
    "visits": 34850
  },
  {
    "id": 18626777,
    "date": "2023-11-11",
    "report_name": "os",
    "report_agency": null,
    "os": "Tizen",
    "visits": 1024
  },
  {
    "id": 18626778,
    "date": "2023-11-11",
    "report_name": "os",
    "report_agency": null,
    "os": "OS/2",
    "visits": 535
  },
  {
    "id": 18626779,
    "date": "2023-11-11",
    "report_name": "os",
    "report_agency": null,
    "os": "Fuchsia",
    "visits": 524
  },
  {
    "id": 18626780,
    "date": "2023-11-11",
    "report_name": "os",
    "report_agency": null,
    "os": "Firefox OS",
    "visits": 370
  },
  {
    "id": 18626781,
    "date": "2023-11-11",
    "report_name": "os",
    "report_agency": null,
    "os": "Playstation 4",
    "visits": 360
  },
  {
    "id": 18626782,
    "date": "2023-11-11",
    "report_name": "os",
    "report_agency": null,
    "os": "BlackBerry",
    "visits": 112
  },
  {
    "id": 18626783,
    "date": "2023-11-11",
    "report_name": "os",
    "report_agency": null,
    "os": "FreeBSD",
    "visits": 61
  },
  {
    "id": 18586927,
    "date": "2023-11-10",
    "report_name": "os",
    "report_agency": null,
    "os": "iOS",
    "visits": 14542134
  },
  {
    "id": 18586928,
    "date": "2023-11-10",
    "report_name": "os",
    "report_agency": null,
    "os": "Windows",
    "visits": 10371996
  },
  {
    "id": 18586929,
    "date": "2023-11-10",
    "report_name": "os",
    "report_agency": null,
    "os": "Android",
    "visits": 7509655
  },
  {
    "id": 18586930,
    "date": "2023-11-10",
    "report_name": "os",
    "report_agency": null,
    "os": "Macintosh",
    "visits": 3625120
  },
  {
    "id": 18586931,
    "date": "2023-11-10",
    "report_name": "os",
    "report_agency": null,
    "os": "Linux",
    "visits": 992683
  },
  {
    "id": 18586932,
    "date": "2023-11-10",
    "report_name": "os",
    "report_agency": null,
    "os": "Chrome OS",
    "visits": 721940
  },
  {
    "id": 18586933,
    "date": "2023-11-10",
    "report_name": "os",
    "report_agency": null,
    "os": "(not set)",
    "visits": 25829
  },
  {
    "id": 18586934,
    "date": "2023-11-10",
    "report_name": "os",
    "report_agency": null,
    "os": "Tizen",
    "visits": 1104
  },
  {
    "id": 18586935,
    "date": "2023-11-10",
    "report_name": "os",
    "report_agency": null,
    "os": "OS/2",
    "visits": 627
  },
  {
    "id": 18586936,
    "date": "2023-11-10",
    "report_name": "os",
    "report_agency": null,
    "os": "Fuchsia",
    "visits": 550
  },
  {
    "id": 18586937,
    "date": "2023-11-10",
    "report_name": "os",
    "report_agency": null,
    "os": "Firefox OS",
    "visits": 377
  },
  {
    "id": 18586938,
    "date": "2023-11-10",
    "report_name": "os",
    "report_agency": null,
    "os": "Playstation 4",
    "visits": 325
  },
  {
    "id": 18586939,
    "date": "2023-11-10",
    "report_name": "os",
    "report_agency": null,
    "os": "BlackBerry",
    "visits": 131
  },
  {
    "id": 18586940,
    "date": "2023-11-10",
    "report_name": "os",
    "report_agency": null,
    "os": "FreeBSD",
    "visits": 81
  },
  {
    "id": 18586941,
    "date": "2023-11-10",
    "report_name": "os",
    "report_agency": null,
    "os": "Samsung",
    "visits": 52
  },
  {
    "id": 18541666,
    "date": "2023-11-09",
    "report_name": "os",
    "report_agency": null,
    "os": "iOS",
    "visits": 15390447
  },
  {
    "id": 18541667,
    "date": "2023-11-09",
    "report_name": "os",
    "report_agency": null,
    "os": "Windows",
    "visits": 14786793
  },
  {
    "id": 18541668,
    "date": "2023-11-09",
    "report_name": "os",
    "report_agency": null,
    "os": "Android",
    "visits": 8196257
  },
  {
    "id": 18541669,
    "date": "2023-11-09",
    "report_name": "os",
    "report_agency": null,
    "os": "Macintosh",
    "visits": 4334611
  },
  {
    "id": 18541670,
    "date": "2023-11-09",
    "report_name": "os",
    "report_agency": null,
    "os": "Chrome OS",
    "visits": 1128304
  },
  {
    "id": 18541671,
    "date": "2023-11-09",
    "report_name": "os",
    "report_agency": null,
    "os": "Linux",
    "visits": 1041718
  },
  {
    "id": 18541672,
    "date": "2023-11-09",
    "report_name": "os",
    "report_agency": null,
    "os": "(not set)",
    "visits": 29023
  },
  {
    "id": 18541673,
    "date": "2023-11-09",
    "report_name": "os",
    "report_agency": null,
    "os": "Tizen",
    "visits": 1165
  },
  {
    "id": 18541674,
    "date": "2023-11-09",
    "report_name": "os",
    "report_agency": null,
    "os": "OS/2",
    "visits": 646
  },
  {
    "id": 18541675,
    "date": "2023-11-09",
    "report_name": "os",
    "report_agency": null,
    "os": "Fuchsia",
    "visits": 642
  },
  {
    "id": 18541676,
    "date": "2023-11-09",
    "report_name": "os",
    "report_agency": null,
    "os": "Firefox OS",
    "visits": 438
  },
  {
    "id": 18541677,
    "date": "2023-11-09",
    "report_name": "os",
    "report_agency": null,
    "os": "Playstation 4",
    "visits": 318
  },
  {
    "id": 18541678,
    "date": "2023-11-09",
    "report_name": "os",
    "report_agency": null,
    "os": "BlackBerry",
    "visits": 144
  },
  {
    "id": 18541679,
    "date": "2023-11-09",
    "report_name": "os",
    "report_agency": null,
    "os": "FreeBSD",
    "visits": 78
  },
  {
    "id": 18541680,
    "date": "2023-11-09",
    "report_name": "os",
    "report_agency": null,
    "os": "UNIX",
    "visits": 71
  },
  {
    "id": 18541681,
    "date": "2023-11-09",
    "report_name": "os",
    "report_agency": null,
    "os": "Samsung",
    "visits": 53
  },
  {
    "id": 18495450,
    "date": "2023-11-08",
    "report_name": "os",
    "report_agency": null,
    "os": "iOS",
    "visits": 15541998
  },
  {
    "id": 18495451,
    "date": "2023-11-08",
    "report_name": "os",
    "report_agency": null,
    "os": "Windows",
    "visits": 15172327
  },
  {
    "id": 18495452,
    "date": "2023-11-08",
    "report_name": "os",
    "report_agency": null,
    "os": "Android",
    "visits": 8091473
  },
  {
    "id": 18495453,
    "date": "2023-11-08",
    "report_name": "os",
    "report_agency": null,
    "os": "Macintosh",
    "visits": 4574565
  },
  {
    "id": 18495454,
    "date": "2023-11-08",
    "report_name": "os",
    "report_agency": null,
    "os": "Chrome OS",
    "visits": 1218104
  },
  {
    "id": 18495455,
    "date": "2023-11-08",
    "report_name": "os",
    "report_agency": null,
    "os": "Linux",
    "visits": 1201331
  },
  {
    "id": 18495456,
    "date": "2023-11-08",
    "report_name": "os",
    "report_agency": null,
    "os": "(not set)",
    "visits": 28943
  },
  {
    "id": 18495457,
    "date": "2023-11-08",
    "report_name": "os",
    "report_agency": null,
    "os": "Tizen",
    "visits": 1145
  },
  {
    "id": 18495458,
    "date": "2023-11-08",
    "report_name": "os",
    "report_agency": null,
    "os": "OS/2",
    "visits": 702
  },
  {
    "id": 18495459,
    "date": "2023-11-08",
    "report_name": "os",
    "report_agency": null,
    "os": "Fuchsia",
    "visits": 589
  },
  {
    "id": 18495460,
    "date": "2023-11-08",
    "report_name": "os",
    "report_agency": null,
    "os": "Firefox OS",
    "visits": 435
  },
  {
    "id": 18495461,
    "date": "2023-11-08",
    "report_name": "os",
    "report_agency": null,
    "os": "FreeBSD",
    "visits": 375
  },
  {
    "id": 18495462,
    "date": "2023-11-08",
    "report_name": "os",
    "report_agency": null,
    "os": "Playstation 4",
    "visits": 305
  },
  {
    "id": 18495463,
    "date": "2023-11-08",
    "report_name": "os",
    "report_agency": null,
    "os": "UNIX",
    "visits": 176
  },
  {
    "id": 18495464,
    "date": "2023-11-08",
    "report_name": "os",
    "report_agency": null,
    "os": "BlackBerry",
    "visits": 142
  },
  {
    "id": 18448690,
    "date": "2023-11-07",
    "report_name": "os",
    "report_agency": null,
    "os": "Windows",
    "visits": 15624336
  },
  {
    "id": 18448691,
    "date": "2023-11-07",
    "report_name": "os",
    "report_agency": null,
    "os": "iOS",
    "visits": 15366142
  },
  {
    "id": 18448692,
    "date": "2023-11-07",
    "report_name": "os",
    "report_agency": null,
    "os": "Android",
    "visits": 8325667
  },
  {
    "id": 18448693,
    "date": "2023-11-07",
    "report_name": "os",
    "report_agency": null,
    "os": "Macintosh",
    "visits": 4600561
  },
  {
    "id": 18448694,
    "date": "2023-11-07",
    "report_name": "os",
    "report_agency": null,
    "os": "Linux",
    "visits": 1172984
  },
  {
    "id": 18448695,
    "date": "2023-11-07",
    "report_name": "os",
    "report_agency": null,
    "os": "Chrome OS",
    "visits": 1034817
  },
  {
    "id": 18448696,
    "date": "2023-11-07",
    "report_name": "os",
    "report_agency": null,
    "os": "(not set)",
    "visits": 30668
  },
  {
    "id": 18448697,
    "date": "2023-11-07",
    "report_name": "os",
    "report_agency": null,
    "os": "FreeBSD",
    "visits": 1716
  },
  {
    "id": 18448698,
    "date": "2023-11-07",
    "report_name": "os",
    "report_agency": null,
    "os": "Tizen",
    "visits": 1138
  },
  {
    "id": 18448699,
    "date": "2023-11-07",
    "report_name": "os",
    "report_agency": null,
    "os": "Fuchsia",
    "visits": 600
  },
  {
    "id": 18448700,
    "date": "2023-11-07",
    "report_name": "os",
    "report_agency": null,
    "os": "OS/2",
    "visits": 591
  },
  {
    "id": 18448701,
    "date": "2023-11-07",
    "report_name": "os",
    "report_agency": null,
    "os": "Firefox OS",
    "visits": 388
  },
  {
    "id": 18448702,
    "date": "2023-11-07",
    "report_name": "os",
    "report_agency": null,
    "os": "Playstation 4",
    "visits": 336
  },
  {
    "id": 18448703,
    "date": "2023-11-07",
    "report_name": "os",
    "report_agency": null,
    "os": "BlackBerry",
    "visits": 137
  },
  {
    "id": 18448704,
    "date": "2023-11-07",
    "report_name": "os",
    "report_agency": null,
    "os": "Samsung",
    "visits": 53
  },
  {
    "id": 18402167,
    "date": "2023-11-06",
    "report_name": "os",
    "report_agency": null,
    "os": "iOS",
    "visits": 16177383
  },
  {
    "id": 18402168,
    "date": "2023-11-06",
    "report_name": "os",
    "report_agency": null,
    "os": "Windows",
    "visits": 15486647
  },
  {
    "id": 18402169,
    "date": "2023-11-06",
    "report_name": "os",
    "report_agency": null,
    "os": "Android",
    "visits": 8390222
  },
  {
    "id": 18402170,
    "date": "2023-11-06",
    "report_name": "os",
    "report_agency": null,
    "os": "Macintosh",
    "visits": 4829984
  },
  {
    "id": 18402171,
    "date": "2023-11-06",
    "report_name": "os",
    "report_agency": null,
    "os": "Linux",
    "visits": 1134682
  },
  {
    "id": 18402172,
    "date": "2023-11-06",
    "report_name": "os",
    "report_agency": null,
    "os": "Chrome OS",
    "visits": 1063789
  },
  {
    "id": 18402173,
    "date": "2023-11-06",
    "report_name": "os",
    "report_agency": null,
    "os": "(not set)",
    "visits": 24023
  },
  {
    "id": 18402174,
    "date": "2023-11-06",
    "report_name": "os",
    "report_agency": null,
    "os": "FreeBSD",
    "visits": 1373
  },
  {
    "id": 18402175,
    "date": "2023-11-06",
    "report_name": "os",
    "report_agency": null,
    "os": "Tizen",
    "visits": 1116
  },
  {
    "id": 18402176,
    "date": "2023-11-06",
    "report_name": "os",
    "report_agency": null,
    "os": "OS/2",
    "visits": 598
  },
  {
    "id": 18402177,
    "date": "2023-11-06",
    "report_name": "os",
    "report_agency": null,
    "os": "Fuchsia",
    "visits": 557
  },
  {
    "id": 18402178,
    "date": "2023-11-06",
    "report_name": "os",
    "report_agency": null,
    "os": "Firefox OS",
    "visits": 420
  },
  {
    "id": 18402179,
    "date": "2023-11-06",
    "report_name": "os",
    "report_agency": null,
    "os": "Playstation 4",
    "visits": 323
  },
  {
    "id": 18402180,
    "date": "2023-11-06",
    "report_name": "os",
    "report_agency": null,
    "os": "BlackBerry",
    "visits": 147
  },
  {
    "id": 18402181,
    "date": "2023-11-06",
    "report_name": "os",
    "report_agency": null,
    "os": "Samsung",
    "visits": 52
  },
  {
    "id": 18365224,
    "date": "2023-11-05",
    "report_name": "os",
    "report_agency": null,
    "os": "iOS",
    "visits": 10469954
  },
  {
    "id": 18365225,
    "date": "2023-11-05",
    "report_name": "os",
    "report_agency": null,
    "os": "Android",
    "visits": 6340223
  },
  {
    "id": 18365226,
    "date": "2023-11-05",
    "report_name": "os",
    "report_agency": null,
    "os": "Windows",
    "visits": 6069046
  },
  {
    "id": 18365227,
    "date": "2023-11-05",
    "report_name": "os",
    "report_agency": null,
    "os": "Macintosh",
    "visits": 3003533
  },
  {
    "id": 18365228,
    "date": "2023-11-05",
    "report_name": "os",
    "report_agency": null,
    "os": "Linux",
    "visits": 955881
  },
  {
    "id": 18365229,
    "date": "2023-11-05",
    "report_name": "os",
    "report_agency": null,
    "os": "Chrome OS",
    "visits": 356137
  },
  {
    "id": 18365230,
    "date": "2023-11-05",
    "report_name": "os",
    "report_agency": null,
    "os": "(not set)",
    "visits": 21735
  },
  {
    "id": 18365231,
    "date": "2023-11-05",
    "report_name": "os",
    "report_agency": null,
    "os": "Tizen",
    "visits": 976
  },
  {
    "id": 18365232,
    "date": "2023-11-05",
    "report_name": "os",
    "report_agency": null,
    "os": "FreeBSD",
    "visits": 699
  },
  {
    "id": 18365233,
    "date": "2023-11-05",
    "report_name": "os",
    "report_agency": null,
    "os": "Fuchsia",
    "visits": 643
  },
  {
    "id": 18365234,
    "date": "2023-11-05",
    "report_name": "os",
    "report_agency": null,
    "os": "OS/2",
    "visits": 569
  },
  {
    "id": 18365235,
    "date": "2023-11-05",
    "report_name": "os",
    "report_agency": null,
    "os": "Firefox OS",
    "visits": 383
  },
  {
    "id": 18365236,
    "date": "2023-11-05",
    "report_name": "os",
    "report_agency": null,
    "os": "Playstation 4",
    "visits": 335
  },
  {
    "id": 18365237,
    "date": "2023-11-05",
    "report_name": "os",
    "report_agency": null,
    "os": "BlackBerry",
    "visits": 119
  },
  {
    "id": 18365238,
    "date": "2023-11-05",
    "report_name": "os",
    "report_agency": null,
    "os": "Samsung",
    "visits": 53
  },
  {
    "id": 18329672,
    "date": "2023-11-04",
    "report_name": "os",
    "report_agency": null,
    "os": "iOS",
    "visits": 12345707
  },
  {
    "id": 18329673,
    "date": "2023-11-04",
    "report_name": "os",
    "report_agency": null,
    "os": "Android",
    "visits": 6518428
  },
  {
    "id": 18329674,
    "date": "2023-11-04",
    "report_name": "os",
    "report_agency": null,
    "os": "Windows",
    "visits": 5429753
  },
  {
    "id": 18329675,
    "date": "2023-11-04",
    "report_name": "os",
    "report_agency": null,
    "os": "Macintosh",
    "visits": 2496993
  },
  {
    "id": 18329676,
    "date": "2023-11-04",
    "report_name": "os",
    "report_agency": null,
    "os": "Linux",
    "visits": 949022
  },
  {
    "id": 18329677,
    "date": "2023-11-04",
    "report_name": "os",
    "report_agency": null,
    "os": "Chrome OS",
    "visits": 280617
  },
  {
    "id": 18329678,
    "date": "2023-11-04",
    "report_name": "os",
    "report_agency": null,
    "os": "(not set)",
    "visits": 26834
  },
  {
    "id": 18329679,
    "date": "2023-11-04",
    "report_name": "os",
    "report_agency": null,
    "os": "Tizen",
    "visits": 991
  },
  {
    "id": 18329680,
    "date": "2023-11-04",
    "report_name": "os",
    "report_agency": null,
    "os": "FreeBSD",
    "visits": 791
  },
  {
    "id": 18329681,
    "date": "2023-11-04",
    "report_name": "os",
    "report_agency": null,
    "os": "OS/2",
    "visits": 551
  },
  {
    "id": 18329682,
    "date": "2023-11-04",
    "report_name": "os",
    "report_agency": null,
    "os": "Fuchsia",
    "visits": 478
  },
  {
    "id": 18329683,
    "date": "2023-11-04",
    "report_name": "os",
    "report_agency": null,
    "os": "Firefox OS",
    "visits": 364
  },
  {
    "id": 18329684,
    "date": "2023-11-04",
    "report_name": "os",
    "report_agency": null,
    "os": "Playstation 4",
    "visits": 313
  },
  {
    "id": 18329685,
    "date": "2023-11-04",
    "report_name": "os",
    "report_agency": null,
    "os": "BlackBerry",
    "visits": 112
  },
  {
    "id": 18329686,
    "date": "2023-11-04",
    "report_name": "os",
    "report_agency": null,
    "os": "Windows Phone",
    "visits": 57
  },
  {
    "id": 18286686,
    "date": "2023-11-03",
    "report_name": "os",
    "report_agency": null,
    "os": "iOS",
    "visits": 14216907
  },
  {
    "id": 18286687,
    "date": "2023-11-03",
    "report_name": "os",
    "report_agency": null,
    "os": "Windows",
    "visits": 12011194
  },
  {
    "id": 18286688,
    "date": "2023-11-03",
    "report_name": "os",
    "report_agency": null,
    "os": "Android",
    "visits": 7427170
  },
  {
    "id": 18286689,
    "date": "2023-11-03",
    "report_name": "os",
    "report_agency": null,
    "os": "Macintosh",
    "visits": 3739753
  },
  {
    "id": 18286690,
    "date": "2023-11-03",
    "report_name": "os",
    "report_agency": null,
    "os": "Linux",
    "visits": 1054827
  },
  {
    "id": 18286691,
    "date": "2023-11-03",
    "report_name": "os",
    "report_agency": null,
    "os": "Chrome OS",
    "visits": 927795
  },
  {
    "id": 18286692,
    "date": "2023-11-03",
    "report_name": "os",
    "report_agency": null,
    "os": "(not set)",
    "visits": 24378
  },
  {
    "id": 18286693,
    "date": "2023-11-03",
    "report_name": "os",
    "report_agency": null,
    "os": "FreeBSD",
    "visits": 1312
  },
  {
    "id": 18286694,
    "date": "2023-11-03",
    "report_name": "os",
    "report_agency": null,
    "os": "Tizen",
    "visits": 1033
  },
  {
    "id": 18286695,
    "date": "2023-11-03",
    "report_name": "os",
    "report_agency": null,
    "os": "OS/2",
    "visits": 564
  },
  {
    "id": 18286696,
    "date": "2023-11-03",
    "report_name": "os",
    "report_agency": null,
    "os": "Fuchsia",
    "visits": 473
  },
  {
    "id": 18286697,
    "date": "2023-11-03",
    "report_name": "os",
    "report_agency": null,
    "os": "Firefox OS",
    "visits": 455
  },
  {
    "id": 18286698,
    "date": "2023-11-03",
    "report_name": "os",
    "report_agency": null,
    "os": "Playstation 4",
    "visits": 342
  },
  {
    "id": 18286699,
    "date": "2023-11-03",
    "report_name": "os",
    "report_agency": null,
    "os": "BlackBerry",
    "visits": 143
  },
  {
    "id": 18286700,
    "date": "2023-11-03",
    "report_name": "os",
    "report_agency": null,
    "os": "Windows Phone",
    "visits": 78
  },
  {
    "id": 18241555,
    "date": "2023-11-02",
    "report_name": "os",
    "report_agency": null,
    "os": "iOS",
    "visits": 14561955
  },
  {
    "id": 18241556,
    "date": "2023-11-02",
    "report_name": "os",
    "report_agency": null,
    "os": "Windows",
    "visits": 14462103
  },
  {
    "id": 18241557,
    "date": "2023-11-02",
    "report_name": "os",
    "report_agency": null,
    "os": "Android",
    "visits": 7924184
  },
  {
    "id": 18241558,
    "date": "2023-11-02",
    "report_name": "os",
    "report_agency": null,
    "os": "Macintosh",
    "visits": 4381931
  },
  {
    "id": 18241559,
    "date": "2023-11-02",
    "report_name": "os",
    "report_agency": null,
    "os": "Chrome OS",
    "visits": 1143219
  },
  {
    "id": 18241560,
    "date": "2023-11-02",
    "report_name": "os",
    "report_agency": null,
    "os": "Linux",
    "visits": 1041332
  },
  {
    "id": 18241561,
    "date": "2023-11-02",
    "report_name": "os",
    "report_agency": null,
    "os": "(not set)",
    "visits": 25315
  },
  {
    "id": 18241562,
    "date": "2023-11-02",
    "report_name": "os",
    "report_agency": null,
    "os": "FreeBSD",
    "visits": 1372
  },
  {
    "id": 18241563,
    "date": "2023-11-02",
    "report_name": "os",
    "report_agency": null,
    "os": "Tizen",
    "visits": 1066
  },
  {
    "id": 18241564,
    "date": "2023-11-02",
    "report_name": "os",
    "report_agency": null,
    "os": "OS/2",
    "visits": 564
  },
  {
    "id": 18241565,
    "date": "2023-11-02",
    "report_name": "os",
    "report_agency": null,
    "os": "Fuchsia",
    "visits": 526
  },
  {
    "id": 18241566,
    "date": "2023-11-02",
    "report_name": "os",
    "report_agency": null,
    "os": "Firefox OS",
    "visits": 457
  },
  {
    "id": 18241567,
    "date": "2023-11-02",
    "report_name": "os",
    "report_agency": null,
    "os": "Playstation 4",
    "visits": 296
  },
  {
    "id": 18241568,
    "date": "2023-11-02",
    "report_name": "os",
    "report_agency": null,
    "os": "BlackBerry",
    "visits": 135
  },
  {
    "id": 18241569,
    "date": "2023-11-02",
    "report_name": "os",
    "report_agency": null,
    "os": "Windows Phone",
    "visits": 86
  },
  {
    "id": 18241570,
    "date": "2023-11-02",
    "report_name": "os",
    "report_agency": null,
    "os": "OpenBSD",
    "visits": 55
  },
  {
    "id": 18196099,
    "date": "2023-11-01",
    "report_name": "os",
    "report_agency": null,
    "os": "Windows",
    "visits": 15458810
  },
  {
    "id": 18196100,
    "date": "2023-11-01",
    "report_name": "os",
    "report_agency": null,
    "os": "iOS",
    "visits": 14837630
  },
  {
    "id": 18196101,
    "date": "2023-11-01",
    "report_name": "os",
    "report_agency": null,
    "os": "Android",
    "visits": 7619945
  },
  {
    "id": 18196102,
    "date": "2023-11-01",
    "report_name": "os",
    "report_agency": null,
    "os": "Macintosh",
    "visits": 4441868
  },
  {
    "id": 18196103,
    "date": "2023-11-01",
    "report_name": "os",
    "report_agency": null,
    "os": "Linux",
    "visits": 1105367
  },
  {
    "id": 18196104,
    "date": "2023-11-01",
    "report_name": "os",
    "report_agency": null,
    "os": "Chrome OS",
    "visits": 1064248
  },
  {
    "id": 18196105,
    "date": "2023-11-01",
    "report_name": "os",
    "report_agency": null,
    "os": "(not set)",
    "visits": 26113
  },
  {
    "id": 18196106,
    "date": "2023-11-01",
    "report_name": "os",
    "report_agency": null,
    "os": "FreeBSD",
    "visits": 1237
  },
  {
    "id": 18196107,
    "date": "2023-11-01",
    "report_name": "os",
    "report_agency": null,
    "os": "Tizen",
    "visits": 1026
  },
  {
    "id": 18196108,
    "date": "2023-11-01",
    "report_name": "os",
    "report_agency": null,
    "os": "OS/2",
    "visits": 602
  },
  {
    "id": 18196109,
    "date": "2023-11-01",
    "report_name": "os",
    "report_agency": null,
    "os": "Fuchsia",
    "visits": 496
  },
  {
    "id": 18196110,
    "date": "2023-11-01",
    "report_name": "os",
    "report_agency": null,
    "os": "Firefox OS",
    "visits": 476
  },
  {
    "id": 18196111,
    "date": "2023-11-01",
    "report_name": "os",
    "report_agency": null,
    "os": "Playstation 4",
    "visits": 395
  },
  {
    "id": 18196112,
    "date": "2023-11-01",
    "report_name": "os",
    "report_agency": null,
    "os": "BlackBerry",
    "visits": 149
  },
  {
    "id": 18196113,
    "date": "2023-11-01",
    "report_name": "os",
    "report_agency": null,
    "os": "Windows Phone",
    "visits": 100
  },
  {
    "id": 18196114,
    "date": "2023-11-01",
    "report_name": "os",
    "report_agency": null,
    "os": "OpenBSD",
    "visits": 62
  },
  {
    "id": 18196115,
    "date": "2023-11-01",
    "report_name": "os",
    "report_agency": null,
    "os": "UNIX",
    "visits": 51
  }
]